{
 "cwbdata": {
  "@xmlns": "urn:cwb.gov.tw:cwbdata-0.1",
  "@xmlns:xsi": "http://www.w3.org/2001/XMLSchema-instance",
  "@xsi:schemaLocation": "urn:cwb.gov.tw:cwbdata-0.1 http://odtest.cwb.gov.tw/XSD/CWB-data-0.1.xsd",
  "identifier": "472c7047-eb48-4aa1-8fc0-9be46a234889",
  "datasetID": "F-AMD-2001",
  "datasetName": "農業氣象預報",
  "dataItemID": "F-AMD-2001-00001",
  "sender": "weather@cwb.gov.tw",
  "sent": "2022-03-18T17:58:03+08:00",
  "status": "Actual",
  "scope": "Public",
  "msgType": "Issue",
  "publisherOID": "2.16.886.101.20003.20008.20004",
  "resources": {
   "resource": {
    "metadata": {
     "resourceName": "中央氣象局氣候服務_農業氣象一週預報",
     "resourceDescription": "提供氣象局預報資料和農事建議，供農業相關單位及農民參考",
     "language": "zh",
     "homepage": "https://www.cwb.gov.tw/V7/forecast/week/w44.htm",
     "sources": {
      "source": [
       {
        "title": "1週預報",
        "path": "https://www.cwb.gov.tw/V7/forecast/week/week.htm"
       },
       {
        "title": "長期天氣預報-季長期天氣展望",
        "path": "https://opendata.cwb.gov.tw/catalog%3fgroup%3df%26dataid%3dA0013-002"
       },
       {
        "title": "天氣特報-豪大雨特報",
        "path": "https://opendata.cwb.gov.tw/catalog%3fgroup%3dw%26dataid%3dC0033-003"
       }
      ]
     },
     "temporal": {
      "issueTime": "2022-03-18T17:00:00+08:00",
      "validTime": {
       "startTime": "2022-03-19T00:00:00+08:00",
       "endTime": "2022-03-26T00:00:00+08:00"
      }
     },
     "weatherElements": {
      "weatherElement": [
       {
        "tagName": "weather",
        "description": "天氣描述"
       },
       {
        "tagName": "temperature",
        "description": "氣溫",
        "units": "˚C"
       },
       {
        "tagName": "agrWeatherForecasts",
        "description": "一週農業天氣預報"
       },
       {
        "tagName": "weatherProfile",
        "description": "天氣概況"
       },
       {
        "tagName": "weatherForecasts",
        "description": "天氣預報"
       },
       {
        "tagName": "agrAdvices",
        "description": "農事建議"
       },
       {
        "tagName": "degreeDay",
        "description": "度日(植物發育時所需之有效溫度單位)",
        "units": "GDD"
       },
       {
        "tagName": "accumulatedTemperature",
        "description": "積溫(植物發育過程中，當各生育階段有效溫度累積至一定數值時，即可完成發育。該數值即稱為此一發育階段所需的積溫。)",
        "units": "ATU"
       },
       {
        "tagName": "cardinalTemperatures",
        "description": "作物生長溫度區間",
        "units": "˚C",
        "statisticalMethods": {
         "statisticalMethod": [
          {
           "methodTagName": "minimum",
           "description": "生長最低溫"
          },
          {
           "methodTagName": "maximum",
           "description": "生長最高溫"
          },
          {
           "methodTagName": "optimum",
           "description": "生長最適溫"
          }
         ]
        }
       },
       {
        "tagName": "growingDays",
        "description": "生育日數"
       },
       {
        "tagName": "cropStatistics",
        "description": "農業積溫統計"
       },
       {
        "tagName": "agrReport",
        "description": "其他建議"
       },
       {
        "tagName": "section",
        "description": "其他建議主段落"
       },
       {
        "tagName": "subsection",
        "description": "其他建議副段落"
       }
      ]
     }
    },
    "data": {
     "agrWeatherForecasts": {
      "weatherProfile": "19日清晨北部及東北部天氣較涼,南部地區有零星短暫雨,白天起東北季風減弱,北部及東北部氣溫稍回升;19日、20日東半部地區有局部陣雨,其中沿海地區有局部大雨發生的機率,西半部地區為多雲到晴,20日午後山區亦有零星短暫陣雨。21日東半部地區有局部短暫陣雨,其他地區為多雲到晴,午後山區亦有零星短暫陣雨。22日另一鋒面通過及東北季風再增強,北部及東北部天氣轉涼;中部以北及東半部地區有局部短暫陣雨或雷雨,南部山區亦有零星短暫陣雨或雷雨,南部平地為多雲。23日、24日東北季風及華南雲雨區影響,北部及東北部天氣較涼;北部地區有短暫雨,中部及東半部地區有局部短暫雨,南部山區亦有零星短暫雨,南部平地為多雲。25日東北季風減弱,北部及東北部氣溫稍回升,北部及東半部地區有局部短暫雨,中南部山區亦有零星短暫雨,中南部平地多雲到晴。20日至22日金門及馬祖易有局部霧或低雲影響能見度,夜間至清晨西半部地區易有局部霧或低雲影響能見度,請注意。19日及23日基隆北海岸、東北部及東部沿海地區有長浪發生的機率,請注意。",
      "weatherForecasts": {
       "location": [
        {
         "locationName": "北部地區",
         "weatherElements": {
          "Wx": {
           "daily": [
            {
             "dataDate": "2022-03-19",
             "weather": "晴時多雲",
             "weatherid": "2"
            },
            {
             "dataDate": "2022-03-20",
             "weather": "晴時多雲",
             "weatherid": "2"
            },
            {
             "dataDate": "2022-03-21",
             "weather": "晴時多雲",
             "weatherid": "2"
            },
            {
             "dataDate": "2022-03-22",
             "weather": "陰時多雲短暫陣雨或雷雨",
             "weatherid": "17"
            },
            {
             "dataDate": "2022-03-23",
             "weather": "陰短暫雨",
             "weatherid": "11"
            },
            {
             "dataDate": "2022-03-24",
             "weather": "陰時多雲短暫雨",
             "weatherid": "10"
            },
            {
             "dataDate": "2022-03-25",
             "weather": "多雲時陰",
             "weatherid": "5"
            }
           ]
          },
          "MaxT": {
           "daily": [
            {
             "dataDate": "2022-03-19",
             "temperature": "26"
            },
            {
             "dataDate": "2022-03-20",
             "temperature": "28"
            },
            {
             "dataDate": "2022-03-21",
             "temperature": "30"
            },
            {
             "dataDate": "2022-03-22",
             "temperature": "24"
            },
            {
             "dataDate": "2022-03-23",
             "temperature": "20"
            },
            {
             "dataDate": "2022-03-24",
             "temperature": "23"
            },
            {
             "dataDate": "2022-03-25",
             "temperature": "26"
            }
           ]
          },
          "MinT": {
           "daily": [
            {
             "dataDate": "2022-03-19",
             "temperature": "17"
            },
            {
             "dataDate": "2022-03-20",
             "temperature": "17"
            },
            {
             "dataDate": "2022-03-21",
             "temperature": "18"
            },
            {
             "dataDate": "2022-03-22",
             "temperature": "18"
            },
            {
             "dataDate": "2022-03-23",
             "temperature": "16"
            },
            {
             "dataDate": "2022-03-24",
             "temperature": "15"
            },
            {
             "dataDate": "2022-03-25",
             "temperature": "17"
            }
           ]
          }
         }
        },
        {
         "locationName": "中部地區",
         "weatherElements": {
          "Wx": {
           "daily": [
            {
             "dataDate": "2022-03-19",
             "weather": "晴時多雲",
             "weatherid": "2"
            },
            {
             "dataDate": "2022-03-20",
             "weather": "晴時多雲",
             "weatherid": "2"
            },
            {
             "dataDate": "2022-03-21",
             "weather": "晴時多雲",
             "weatherid": "2"
            },
            {
             "dataDate": "2022-03-22",
             "weather": "多雲短暫陣雨或雷雨",
             "weatherid": "15"
            },
            {
             "dataDate": "2022-03-23",
             "weather": "陰短暫雨",
             "weatherid": "11"
            },
            {
             "dataDate": "2022-03-24",
             "weather": "多雲時陰短暫雨",
             "weatherid": "9"
            },
            {
             "dataDate": "2022-03-25",
             "weather": "多雲時陰",
             "weatherid": "5"
            }
           ]
          },
          "MaxT": {
           "daily": [
            {
             "dataDate": "2022-03-19",
             "temperature": "29"
            },
            {
             "dataDate": "2022-03-20",
             "temperature": "31"
            },
            {
             "dataDate": "2022-03-21",
             "temperature": "32"
            },
            {
             "dataDate": "2022-03-22",
             "temperature": "30"
            },
            {
             "dataDate": "2022-03-23",
             "temperature": "23"
            },
            {
             "dataDate": "2022-03-24",
             "temperature": "26"
            },
            {
             "dataDate": "2022-03-25",
             "temperature": "27"
            }
           ]
          },
          "MinT": {
           "daily": [
            {
             "dataDate": "2022-03-19",
             "temperature": "19"
            },
            {
             "dataDate": "2022-03-20",
             "temperature": "18"
            },
            {
             "dataDate": "2022-03-21",
             "temperature": "20"
            },
            {
             "dataDate": "2022-03-22",
             "temperature": "20"
            },
            {
             "dataDate": "2022-03-23",
             "temperature": "17"
            },
            {
             "dataDate": "2022-03-24",
             "temperature": "16"
            },
            {
             "dataDate": "2022-03-25",
             "temperature": "18"
            }
           ]
          }
         }
        },
        {
         "locationName": "南部地區",
         "weatherElements": {
          "Wx": {
           "daily": [
            {
             "dataDate": "2022-03-19",
             "weather": "多雲短暫雨",
             "weatherid": "8"
            },
            {
             "dataDate": "2022-03-20",
             "weather": "晴時多雲",
             "weatherid": "2"
            },
            {
             "dataDate": "2022-03-21",
             "weather": "晴時多雲",
             "weatherid": "2"
            },
            {
             "dataDate": "2022-03-22",
             "weather": "晴時多雲",
             "weatherid": "2"
            },
            {
             "dataDate": "2022-03-23",
             "weather": "陰天",
             "weatherid": "7"
            },
            {
             "dataDate": "2022-03-24",
             "weather": "陰時多雲短暫雨",
             "weatherid": "10"
            },
            {
             "dataDate": "2022-03-25",
             "weather": "多雲時晴",
             "weatherid": "3"
            }
           ]
          },
          "MaxT": {
           "daily": [
            {
             "dataDate": "2022-03-19",
             "temperature": "29"
            },
            {
             "dataDate": "2022-03-20",
             "temperature": "31"
            },
            {
             "dataDate": "2022-03-21",
             "temperature": "33"
            },
            {
             "dataDate": "2022-03-22",
             "temperature": "32"
            },
            {
             "dataDate": "2022-03-23",
             "temperature": "29"
            },
            {
             "dataDate": "2022-03-24",
             "temperature": "28"
            },
            {
             "dataDate": "2022-03-25",
             "temperature": "30"
            }
           ]
          },
          "MinT": {
           "daily": [
            {
             "dataDate": "2022-03-19",
             "temperature": "22"
            },
            {
             "dataDate": "2022-03-20",
             "temperature": "20"
            },
            {
             "dataDate": "2022-03-21",
             "temperature": "21"
            },
            {
             "dataDate": "2022-03-22",
             "temperature": "24"
            },
            {
             "dataDate": "2022-03-23",
             "temperature": "20"
            },
            {
             "dataDate": "2022-03-24",
             "temperature": "19"
            },
            {
             "dataDate": "2022-03-25",
             "temperature": "19"
            }
           ]
          }
         }
        },
        {
         "locationName": "東北部地區",
         "weatherElements": {
          "Wx": {
           "daily": [
            {
             "dataDate": "2022-03-19",
             "weather": "多雲時陰陣雨",
             "weatherid": "12"
            },
            {
             "dataDate": "2022-03-20",
             "weather": "陰時多雲陣雨",
             "weatherid": "13"
            },
            {
             "dataDate": "2022-03-21",
             "weather": "多雲短暫陣雨",
             "weatherid": "8"
            },
            {
             "dataDate": "2022-03-22",
             "weather": "陰時多雲短暫陣雨或雷雨",
             "weatherid": "17"
            },
            {
             "dataDate": "2022-03-23",
             "weather": "陰短暫雨",
             "weatherid": "11"
            },
            {
             "dataDate": "2022-03-24",
             "weather": "陰短暫雨",
             "weatherid": "11"
            },
            {
             "dataDate": "2022-03-25",
             "weather": "陰時多雲",
             "weatherid": "6"
            }
           ]
          },
          "MaxT": {
           "daily": [
            {
             "dataDate": "2022-03-19",
             "temperature": "24"
            },
            {
             "dataDate": "2022-03-20",
             "temperature": "25"
            },
            {
             "dataDate": "2022-03-21",
             "temperature": "28"
            },
            {
             "dataDate": "2022-03-22",
             "temperature": "24"
            },
            {
             "dataDate": "2022-03-23",
             "temperature": "22"
            },
            {
             "dataDate": "2022-03-24",
             "temperature": "23"
            },
            {
             "dataDate": "2022-03-25",
             "temperature": "25"
            }
           ]
          },
          "MinT": {
           "daily": [
            {
             "dataDate": "2022-03-19",
             "temperature": "17"
            },
            {
             "dataDate": "2022-03-20",
             "temperature": "19"
            },
            {
             "dataDate": "2022-03-21",
             "temperature": "20"
            },
            {
             "dataDate": "2022-03-22",
             "temperature": "18"
            },
            {
             "dataDate": "2022-03-23",
             "temperature": "17"
            },
            {
             "dataDate": "2022-03-24",
             "temperature": "16"
            },
            {
             "dataDate": "2022-03-25",
             "temperature": "18"
            }
           ]
          }
         }
        },
        {
         "locationName": "東部地區",
         "weatherElements": {
          "Wx": {
           "daily": [
            {
             "dataDate": "2022-03-19",
             "weather": "陰陣雨",
             "weatherid": "14"
            },
            {
             "dataDate": "2022-03-20",
             "weather": "陰陣雨",
             "weatherid": "14"
            },
            {
             "dataDate": "2022-03-21",
             "weather": "多雲短暫陣雨",
             "weatherid": "8"
            },
            {
             "dataDate": "2022-03-22",
             "weather": "多雲短暫陣雨或雷雨",
             "weatherid": "15"
            },
            {
             "dataDate": "2022-03-23",
             "weather": "陰短暫雨",
             "weatherid": "11"
            },
            {
             "dataDate": "2022-03-24",
             "weather": "陰短暫雨",
             "weatherid": "11"
            },
            {
             "dataDate": "2022-03-25",
             "weather": "陰短暫雨",
             "weatherid": "11"
            }
           ]
          },
          "MaxT": {
           "daily": [
            {
             "dataDate": "2022-03-19",
             "temperature": "24"
            },
            {
             "dataDate": "2022-03-20",
             "temperature": "25"
            },
            {
             "dataDate": "2022-03-21",
             "temperature": "27"
            },
            {
             "dataDate": "2022-03-22",
             "temperature": "26"
            },
            {
             "dataDate": "2022-03-23",
             "temperature": "23"
            },
            {
             "dataDate": "2022-03-24",
             "temperature": "24"
            },
            {
             "dataDate": "2022-03-25",
             "temperature": "25"
            }
           ]
          },
          "MinT": {
           "daily": [
            {
             "dataDate": "2022-03-19",
             "temperature": "19"
            },
            {
             "dataDate": "2022-03-20",
             "temperature": "20"
            },
            {
             "dataDate": "2022-03-21",
             "temperature": "20"
            },
            {
             "dataDate": "2022-03-22",
             "temperature": "22"
            },
            {
             "dataDate": "2022-03-23",
             "temperature": "20"
            },
            {
             "dataDate": "2022-03-24",
             "temperature": "19"
            },
            {
             "dataDate": "2022-03-25",
             "temperature": "19"
            }
           ]
          }
         }
        },
        {
         "locationName": "東南部地區",
         "weatherElements": {
          "Wx": {
           "daily": [
            {
             "dataDate": "2022-03-19",
             "weather": "陰陣雨",
             "weatherid": "14"
            },
            {
             "dataDate": "2022-03-20",
             "weather": "陰陣雨",
             "weatherid": "14"
            },
            {
             "dataDate": "2022-03-21",
             "weather": "晴時多雲",
             "weatherid": "2"
            },
            {
             "dataDate": "2022-03-22",
             "weather": "多雲短暫陣雨或雷雨",
             "weatherid": "15"
            },
            {
             "dataDate": "2022-03-23",
             "weather": "陰短暫雨",
             "weatherid": "11"
            },
            {
             "dataDate": "2022-03-24",
             "weather": "陰短暫雨",
             "weatherid": "11"
            },
            {
             "dataDate": "2022-03-25",
             "weather": "陰天",
             "weatherid": "7"
            }
           ]
          },
          "MaxT": {
           "daily": [
            {
             "dataDate": "2022-03-19",
             "temperature": "26"
            },
            {
             "dataDate": "2022-03-20",
             "temperature": "26"
            },
            {
             "dataDate": "2022-03-21",
             "temperature": "27"
            },
            {
             "dataDate": "2022-03-22",
             "temperature": "28"
            },
            {
             "dataDate": "2022-03-23",
             "temperature": "25"
            },
            {
             "dataDate": "2022-03-24",
             "temperature": "25"
            },
            {
             "dataDate": "2022-03-25",
             "temperature": "26"
            }
           ]
          },
          "MinT": {
           "daily": [
            {
             "dataDate": "2022-03-19",
             "temperature": "20"
            },
            {
             "dataDate": "2022-03-20",
             "temperature": "20"
            },
            {
             "dataDate": "2022-03-21",
             "temperature": "21"
            },
            {
             "dataDate": "2022-03-22",
             "temperature": "22"
            },
            {
             "dataDate": "2022-03-23",
             "temperature": "21"
            },
            {
             "dataDate": "2022-03-24",
             "temperature": "20"
            },
            {
             "dataDate": "2022-03-25",
             "temperature": "20"
            }
           ]
          }
         }
        }
       ]
      },
      "agrAdvices": {
       "agrForecasts": {
        "location": [
         {
          "locationName": "北部地區",
          "weatherElements": {
           "daily": [
            {
             "dataDate": "2022-03-19",
             "degreeDay": "11.5",
             "accumulatedTemperature": "11.5"
            },
            {
             "dataDate": "2022-03-20",
             "degreeDay": "12.5",
             "accumulatedTemperature": "24.0"
            },
            {
             "dataDate": "2022-03-21",
             "degreeDay": "14.0",
             "accumulatedTemperature": "38.0"
            },
            {
             "dataDate": "2022-03-22",
             "degreeDay": "11.0",
             "accumulatedTemperature": "49.0"
            },
            {
             "dataDate": "2022-03-23",
             "degreeDay": "8.0",
             "accumulatedTemperature": "57.0"
            },
            {
             "dataDate": "2022-03-24",
             "degreeDay": "9.0",
             "accumulatedTemperature": "66.0"
            },
            {
             "dataDate": "2022-03-25",
             "degreeDay": "11.5",
             "accumulatedTemperature": "77.5"
            }
           ]
          }
         },
         {
          "locationName": "中部地區",
          "weatherElements": {
           "daily": [
            {
             "dataDate": "2022-03-19",
             "degreeDay": "14.0",
             "accumulatedTemperature": "14.0"
            },
            {
             "dataDate": "2022-03-20",
             "degreeDay": "14.5",
             "accumulatedTemperature": "28.5"
            },
            {
             "dataDate": "2022-03-21",
             "degreeDay": "16.0",
             "accumulatedTemperature": "44.5"
            },
            {
             "dataDate": "2022-03-22",
             "degreeDay": "15.0",
             "accumulatedTemperature": "59.5"
            },
            {
             "dataDate": "2022-03-23",
             "degreeDay": "10.0",
             "accumulatedTemperature": "69.5"
            },
            {
             "dataDate": "2022-03-24",
             "degreeDay": "11.0",
             "accumulatedTemperature": "80.5"
            },
            {
             "dataDate": "2022-03-25",
             "degreeDay": "12.5",
             "accumulatedTemperature": "93.0"
            }
           ]
          }
         },
         {
          "locationName": "南部地區",
          "weatherElements": {
           "daily": [
            {
             "dataDate": "2022-03-19",
             "degreeDay": "15.5",
             "accumulatedTemperature": "15.5"
            },
            {
             "dataDate": "2022-03-20",
             "degreeDay": "15.5",
             "accumulatedTemperature": "31.0"
            },
            {
             "dataDate": "2022-03-21",
             "degreeDay": "17.0",
             "accumulatedTemperature": "48.0"
            },
            {
             "dataDate": "2022-03-22",
             "degreeDay": "18.0",
             "accumulatedTemperature": "66.0"
            },
            {
             "dataDate": "2022-03-23",
             "degreeDay": "14.5",
             "accumulatedTemperature": "80.5"
            },
            {
             "dataDate": "2022-03-24",
             "degreeDay": "13.5",
             "accumulatedTemperature": "94.0"
            },
            {
             "dataDate": "2022-03-25",
             "degreeDay": "14.5",
             "accumulatedTemperature": "108.5"
            }
           ]
          }
         },
         {
          "locationName": "東北部地區",
          "weatherElements": {
           "daily": [
            {
             "dataDate": "2022-03-19",
             "degreeDay": "10.5",
             "accumulatedTemperature": "10.5"
            },
            {
             "dataDate": "2022-03-20",
             "degreeDay": "12.0",
             "accumulatedTemperature": "22.5"
            },
            {
             "dataDate": "2022-03-21",
             "degreeDay": "14.0",
             "accumulatedTemperature": "36.5"
            },
            {
             "dataDate": "2022-03-22",
             "degreeDay": "11.0",
             "accumulatedTemperature": "47.5"
            },
            {
             "dataDate": "2022-03-23",
             "degreeDay": "9.5",
             "accumulatedTemperature": "57.0"
            },
            {
             "dataDate": "2022-03-24",
             "degreeDay": "9.5",
             "accumulatedTemperature": "66.5"
            },
            {
             "dataDate": "2022-03-25",
             "degreeDay": "11.5",
             "accumulatedTemperature": "78.0"
            }
           ]
          }
         },
         {
          "locationName": "東部地區",
          "weatherElements": {
           "daily": [
            {
             "dataDate": "2022-03-19",
             "degreeDay": "11.5",
             "accumulatedTemperature": "11.5"
            },
            {
             "dataDate": "2022-03-20",
             "degreeDay": "12.5",
             "accumulatedTemperature": "24.0"
            },
            {
             "dataDate": "2022-03-21",
             "degreeDay": "13.5",
             "accumulatedTemperature": "37.5"
            },
            {
             "dataDate": "2022-03-22",
             "degreeDay": "14.0",
             "accumulatedTemperature": "51.5"
            },
            {
             "dataDate": "2022-03-23",
             "degreeDay": "11.5",
             "accumulatedTemperature": "63.0"
            },
            {
             "dataDate": "2022-03-24",
             "degreeDay": "11.5",
             "accumulatedTemperature": "74.5"
            },
            {
             "dataDate": "2022-03-25",
             "degreeDay": "12.0",
             "accumulatedTemperature": "86.5"
            }
           ]
          }
         },
         {
          "locationName": "東南部地區",
          "weatherElements": {
           "daily": [
            {
             "dataDate": "2022-03-19",
             "degreeDay": "13.0",
             "accumulatedTemperature": "13.0"
            },
            {
             "dataDate": "2022-03-20",
             "degreeDay": "13.0",
             "accumulatedTemperature": "26.0"
            },
            {
             "dataDate": "2022-03-21",
             "degreeDay": "14.0",
             "accumulatedTemperature": "40.0"
            },
            {
             "dataDate": "2022-03-22",
             "degreeDay": "15.0",
             "accumulatedTemperature": "55.0"
            },
            {
             "dataDate": "2022-03-23",
             "degreeDay": "13.0",
             "accumulatedTemperature": "68.0"
            },
            {
             "dataDate": "2022-03-24",
             "degreeDay": "12.5",
             "accumulatedTemperature": "80.5"
            },
            {
             "dataDate": "2022-03-25",
             "degreeDay": "13.0",
             "accumulatedTemperature": "93.5"
            }
           ]
          }
         }
        ]
       },
       "cropStatistics": {
        "crop": {
         "cropName": "水稻",
         "cardinalTemperatures": {
          "growingStage": {
           "description": "稻作生長溫度",
           "minimum": "10",
           "maximum": "40"
          }
         },
         "location": [
          {
           "locationName": "臺中地區",
           "cropBreed": "臺農67號",
           "statistics": {
            "fifteenYears": {
             "description": "一期稻作生育日數及生育期總積溫(15年平均值)",
             "timePeriod": [
              {
               "description": "插秧至抽穗",
               "growingDays": "83",
               "accumulatedTemperature": "1067.71"
              },
              {
               "description": "插秧至收穫",
               "growingDays": "121",
               "accumulatedTemperature": "1744.07"
              }
             ]
            },
            "thisYear": {
             "description": "111年一期稻作積溫值 (各改良場豐歉試驗臺農67號)",
             "dibblingDate": "2022-02-26",
             "timePeriod": {
              "description": "插秧至本日",
              "startDate": "2022-02-26",
              "endDate": "2022-03-17",
              "growingDays": "20",
              "accumulatedTemperature": "215.55"
             }
            }
           }
          },
          {
           "locationName": "高雄地區",
           "cropBreed": "臺農67號",
           "statistics": {
            "fifteenYears": {
             "description": "一期稻作生育日數及生育期總積溫(15年平均值)",
             "timePeriod": [
              {
               "description": "插秧至抽穗",
               "growingDays": "93",
               "accumulatedTemperature": "1155.48"
              },
              {
               "description": "插秧至收穫",
               "growingDays": "124",
               "accumulatedTemperature": "1699.05"
              }
             ]
            },
            "thisYear": {
             "description": "111年一期稻作積溫值 (各改良場豐歉試驗臺農67號)",
             "dibblingDate": "2022-01-13",
             "timePeriod": {
              "description": "插秧至本日",
              "startDate": "2022-01-13",
              "endDate": "2022-03-17",
              "growingDays": "64",
              "accumulatedTemperature": "729.6"
             }
            }
           }
          },
          {
           "locationName": "花蓮地區",
           "cropBreed": "臺農67號",
           "statistics": {
            "fifteenYears": {
             "description": "一期稻作生育日數及生育期總積溫(15年平均值)",
             "timePeriod": [
              {
               "description": "插秧至抽穗",
               "growingDays": "98",
               "accumulatedTemperature": "1090.23"
              },
              {
               "description": "插秧至收穫",
               "growingDays": "136",
               "accumulatedTemperature": "1697.62"
              }
             ]
            },
            "thisYear": {
             "description": "111年一期稻作積溫值 (各改良場豐歉試驗臺農67號)",
             "dibblingDate": "2022-02-07",
             "timePeriod": {
              "description": "插秧至本日",
              "startDate": "2022-02-07",
              "endDate": "2022-03-17",
              "growingDays": "39",
              "accumulatedTemperature": "365.25"
             }
            }
           }
          }
         ]
        }
       },
       "agrReport": {
        "section": [
         {
          "content": "未來1個月長期天氣展望,預測未來兩週為天氣變化快的春季形態,受鋒面、東北季風增強及華南雲雨區影響期間,各地氣溫略降,有陣雨或雷雨,且部分地區有較大雨勢發生的機率。因春天天氣變化快速,模式掌握能力較低,請隨時留意最新氣象資訊。",
          "subsection": [
           {
            "content": "第1週:平均氣溫預測,各地以「低於」氣候正常值的機率最小;雨量預測,各地以「接近」氣候正常值的機率最大。"
           },
           {
            "content": "第2週:平均氣溫預測,各地以「低於」氣候正常值的機率最小;雨量預測,各地以「接近」氣候正常值的機率最大。"
           },
           {
            "content": "第1~4週:1個月之展望,預測平均氣溫及雨量,各地以「接近」氣候正常值的機率最大。"
           }
          ]
         },
         {
          "content": "農委會主委陳吉仲去年9月開部會之先,成立淨零排放專案辦公室,並盤點國內目前農業可提供的碳權交易超過5百萬公噸,若以國際二氧化碳排放交易的最保守行情1噸50美元計,每年可達2億5000萬美元(約新台幣71.3億元)規模,未來在碳權交易助攻下,將可增加農民收益。",
          "subsection": [
           {
            "content": "台灣去年同時面臨56年來空前的乾旱與水災,氣候變遷衝擊農業部門最鉅,農損金額的高峰點已從2009年的291億元,到2016年的383億元,增加逾3成,且18年後,台灣的整體溫度將上升1.5度,全面衝擊台灣農業。"
           },
           {
            "content": "陳吉仲表示,農業部門6年前已啟動選育抗逆境品種等相關調適策略,但追根究柢還是得要從「淨零」著手,尤其國際能源組織(IEA)已明定28年後不再使用石化能源,並減少二氧化碳排放量,且歐盟明年就逐步實施「碳邊境調整機制」,進口至歐盟的產品都得購買碳權。"
           },
           {
            "content": "台灣要達到淨零排放目標的關鍵之一,陳吉仲認為關鍵在於農業提供的碳匯,農業碳匯可搭配環保署的碳權抵換專案外,在環保署的架構下,參考聯合國CDM(清潔發展機制,Clean DevelopmentMechanism)方法學,以及VCS自願性碳認證標準(Voluntary Carbon Standard)等國際機構的驗證方式,他說農委會不僅會協助農民向環保署申請碳權抵換外,今年以方案型或計畫型協助農民取得碳權,讓農民在農作物收穫以外,可取得收益,由於循環農業等減碳設施需要費用,農民有貸款需求,農委會將推出優惠措施責成綠色金融。"
           },
           {
            "content": "陳吉仲說,農漁畜牧業栽種或養殖過程中,同樣也會產生二氧化碳,農委會推動的循環農業,將力拚農業碳排量降至零,今年就會建立10個示範場域,未來目標建立千個示範場域,不僅透過示範場域建立農業資材、畜牧排泄物等循環利用、沼氣發電模式,也會透過示範場域來評估排碳基準,並且也會透過該場域建立農村發電自給示範點。他強調,台灣超過千座農村社區若都能自行供電,更符合電網分散的國安策略,未來用電有餘還能賣電,也增加農民收入。(參考資料來源:有機農業全球資訊網)"
           }
          ]
         },
         {
          "content": "農金局辦理一系列推廣香蕉收入保險宣導活動,16日來到嘉義縣番路鄉及中埔鄉,由李聰勇局長偕同農險基金林耀東總經理,親自傾聽番路鄉農會盧淑惠總幹事、中埔鄉農會李碧雲總幹事及在地蕉農建議,了解農民對於農業保險需求,李局長表示,嘉義縣部分地區已連續2年獲得理賠,籲請蕉農把握時效,在3月底前到當地農會踴躍投保。",
          "subsection": [
           {
            "content": "李局長指出,為簡政便民並保障實耕者權益,修正投保規定,農民僅需明確填寫相關書表文件所列地號、地段、投保面積等,無須取得租約等佐證資料,即完成投保程序;另參考農民意見,放寬投保資格,刪除不得間作混作規定。為使更多地區蕉農能參與香蕉收入保險,今年新增2縣市、21個鄉(鎮、市、區)作為試辦地區,目前已有高雄市等13縣市、99個鄉(鎮、市、區)參與,同時提供補助1/2保費,部分縣市政府也有加碼補助,減輕農民負擔,鼓勵共同參與。"
           },
           {
            "content": "李局長特別說明,香蕉收入保險保障相當全面,包括因香蕉產量減少及價格下跌所致損失,109年度及110年度連續2年出險理賠均逾600萬元,提供蕉農最實質的保障。香蕉收入保險110年度因上半年受乾旱及8月西南氣流豪雨等災害影響,致部分地區香蕉單位面積產量減少,經核算8縣市、22鄉鎮市區符合香蕉收入保險理賠標準,計有120位投保農民受益,理賠面積約200公頃、理賠金額623萬元,農險基金已於最短時間將理賠款核撥給相關農會轉入農民帳戶。"
           },
           {
            "content": "農金局強調,全球氣候變遷日趨嚴峻,因應極端天氣發生之頻率及強度增加,面臨的災害型態多元,農民可藉由農業保險移轉風險,目前已開發25種品項、39張保單,呼籲農民朋友踴躍投保農業保險,強化災變因應能力,保障營農收入,共同打造安心的從農環境。(參考資料來源:行政院農委會農業金融局)"
           }
          ]
         },
         {
          "content": "為了解決生產雞蛋帶來的環境問題,英國新創公司BetterOrigin於2021年12月22日宣布與英國連鎖超市Morrisons合作,透過超市供應鏈中的剩食作為黑水虻幼蟲的食物,並將其作為加入雞飼料,減少雞飼料中的大豆量,甚至可能生產「碳中和雞蛋」。",
          "subsection": [
           {
            "content": "全球約有數十億隻雞為人類消費而生,而牠們主要以富含穀物和大豆的飲食為生,但這卻是使全球暖化惡化的元兇之一。根據《自然》雜誌2021年發表的研究發現,近19年來大豆產量增長最快的是地方就是巴西的亞馬遜雨林地區,大豆種植面積增加了10倍以上。亞馬遜雨林作為吸收大量二氧化碳的「地球之肺」,正在因為種植大豆持續被威脅,換句話說,以大豆作為飼料的養殖方式導致環境問題。"
           },
           {
            "content": "為了改善上述問題,Better Origin透過將Morrisons超市供應鏈的水果和蔬菜廢物作為餵養黑水虻幼蟲的食物,儼然是一座迷你農場,並在大約2週後收成,作為雞飼料的一部分,取代部分大豆。Better Origin表示,在Morrisons目前設立的10個迷你農場將總共養活32萬隻母雞,每年產下數百萬個雞蛋。減少的大豆可以抵消5737噸二氧化碳,每年節省的量相當於56公頃的南美土地免受森林砍伐。"
           },
           {
            "content": "在Better Origin和Morrisons的合作中,雙方以生產出「碳中和雞蛋」為目標。Better Origin的共同創始人Fotis Fotiadis表示,這些蟲對雞來說是「高營養添加劑」,而不是用來完全取代雞飲食中的大豆,透過將黑水虻幼蟲加入雞蛋供應鏈,不僅在餵養幼蟲時減少全球剩食問題,更重要的是改善雞的整體健康情況,這將導致蛋雞生產更多的雞蛋,將離碳中和越來越近。「我們已經計畫於2030年時,在英國農業供應鏈中實現淨零排放的目標,而這不僅需要創新思維,更需要與我們合作農民的支持。」Morrisons農業部門主管Throup表示,我們想透過推動碳中和的路上持續吸引更多志同道合的人加入,無論是生產者或是消費者,都將成為促成該目標的關鍵。此外,Morrisons預計明年將把碳中和雞蛋推向市場,消費者將可以透過購物選擇,支持碳中和產業鏈。(參考資料來源:農業科技決策資訊平台)"
           }
          ]
         }
        ]
       }
      }
     }
    }
   }
  }
 }
}